sparkler/__init__.py
sparkler/cmd.py
sparkler/tests/__init__.py
sparkler/tests/test_cmd.py
sparkler-0.3.0.dist-info/AUTHORS
sparkler-0.3.0.dist-info/LICENSE
sparkler-0.3.0.dist-info/METADATA
sparkler-0.3.0.dist-info/WHEEL
sparkler-0.3.0.dist-info/entry_points.txt
sparkler-0.3.0.dist-info/pbr.json
sparkler-0.3.0.dist-info/top_level.txt
sparkler-0.3.0.dist-info/RECORD
