Metadata-Version: 2.1
Name: sparkler
Version: 0.3.0
Summary: GitHub stats sparkline CLI
Home-page: http://www.ivehearditbothways.com
Author: Sean McGinnis
Author-email: sean.mcginnis@gmail.com
License: Apache License (2.0)
Keywords: sparklines spark lines
Platform: UNKNOWN
Classifier: Environment :: Console
Classifier: Intended Audience :: Information Technology
Classifier: Intended Audience :: Developers
Classifier: License :: OSI Approved :: Apache Software License
Classifier: Operating System :: POSIX :: Linux
Classifier: Programming Language :: Python
Classifier: Programming Language :: Python :: 3
Classifier: Programming Language :: Python :: 3.7
Requires-Dist: pbr (!=2.1.0,>=2.0.0)
Requires-Dist: requests (>2.20.0)
Requires-Dist: Pillow (>=6.0.0)
Requires-Dist: webcolors (>=1.9.1)
